README
setup.py
udacity_dl.egg-info/PKG-INFO
udacity_dl.egg-info/SOURCES.txt
udacity_dl.egg-info/dependency_links.txt
udacity_dl.egg-info/entry_points.txt
udacity_dl.egg-info/top_level.txt
udacitydl/__init__.py
udacitydl/courses.py
udacitydl/udacitydl.py