Metadata-Version: 1.1
Name: udacity-dl
Version: 1.2.1
Summary: Download udacity class videos and resources
Home-page: https://github.com/riteshpradhan/udacity-dl
Author: Ritesh Pradhan
Author-email: ritesxz@gmail.com
License: UNKNOWN
Download-URL: https://pypi.python.org/pypi/udacity-dl
Platform: UNKNOWN
